check_tier
