Metadata-Version: 1.0
Name: check-tier
Version: 1.0.0.3
Summary: Django app to check tier before deployment.
Home-page: UNKNOWN
Author: Level Up
Author-email: os@lvlup.us
License: GPL v3
Platform: UNKNOWN
